uval/__init__.py
uval/config/README.md
uval/config/__init__.py
uval/config/config_utils.py
uval/config/defaults.py
uval/context.py
uval/data/combine_files.py
uval/data/data_utils.py
uval/data/dataset.py
uval/data/dataset_specification.py
uval/data/hdf5.py
uval/data/stage_data.py
uval/main.py
uval/main_new.py
uval/metrics/metrics.py
uval/metrics/metrics_new.py
uval/metrics/metrics_utils.py
uval/plotting/plot_utils.py
uval/plotting/plotter.py
uval/reporting/report_utils.py
uval/reporting/reporter.py
uval/stages/__init__.py
uval/stages/combine_files.py
uval/stages/dataset_specification.py
uval/stages/diff_reporter.py
uval/stages/hdf5.py
uval/stages/metrics.py
uval/stages/stage.py
uval/stages/stage_data.py
uval/templates/template.html
uval/templates/template_diff.html
uval/templates/template_diff_subclass.html
uval/templates/template_range.html
uval/templates/template_range_diff.html
uval/templates/template_range_subclass.html
uval/templates/template_subclass.html
uval/tests/__init__.py
uval/tests/sample.h5
uval/tests/test_config.py
uval/tests/test_format.py
uval/tests/test_hdf5.py
uval/tests/test_log.py
uval/tests/test_metrics.py
uval/tests/test_naming.py
uval/tests/test_verification.py
uval/tests/test_zdiff.py
uval/utils/__init__.py
uval/utils/average_precision.py
uval/utils/hdf5_format.py
uval/utils/hdf5_io.py
uval/utils/hdf5_verification.py
uval/utils/hdf5_virtual.py
uval/utils/iou.py
uval/utils/label_naming.py
uval/utils/log.py
uval/utils/metric_utils.py
uval/utils/nonblocking_queue.py
uval/utils/yaml_io.py
uval-0.2.2.dist-info/LICENSE
uval-0.2.2.dist-info/METADATA
uval-0.2.2.dist-info/WHEEL
uval-0.2.2.dist-info/entry_points.txt
uval-0.2.2.dist-info/RECORD
