Metadata-Version: 2.1
Name: uval
Version: 0.2.2
Summary: This python package is meant to provide a high level interface to facilitate the evaluation of object detection and segmentation algorithms that operate on 3D volumetric data.
Home-page: https://gitlab.com/smithsdetection/uval
License: GPL-3.0-only
Keywords: evaluation,object detection,3D,x-ray,CT
Author: Geert Heilmann
Author-email: geert.heilmann@smithsdetection.com
Maintainer: Faraz Saeedan
Maintainer-email: faraz.saeedan@smithsdetection.com
Requires-Python: >=3.8,<4.0
Classifier: License :: OSI Approved :: GNU General Public License v3 (GPLv3)
Classifier: Programming Language :: Python :: 3
Classifier: Programming Language :: Python :: 3.8
Classifier: Programming Language :: Python :: 3.9
Classifier: Programming Language :: Python :: 3.10
Classifier: Programming Language :: Python :: 3.11
Classifier: Programming Language :: Python :: 3.12
Requires-Dist: Jinja2 (>=3.0.3,<4.0.0)
Requires-Dist: Pillow (>=9.0.1,<10.0.0)
Requires-Dist: black (>=22.6.0,<23.0.0)
Requires-Dist: click (>=8.0.4,<9.0.0)
Requires-Dist: fvcore (>=0.1.5,<0.2.0)
Requires-Dist: h5py (>=3.6.0,<4.0.0)
Requires-Dist: ipykernel (>=6.9.2,<7.0.0)
Requires-Dist: isort (>=5.12.0)
Requires-Dist: matplotlib (>=3.5.1,<4.0.0)
Requires-Dist: mypy (>=0.971,<0.972)
Requires-Dist: myst-parser (==0.17.0)
Requires-Dist: numpy (>=1.22.3,<2.0.0)
Requires-Dist: pandas (>=1.4.1,<2.0.0)
Requires-Dist: pipx (>=1.0.0,<2.0.0)
Requires-Dist: pylint (>=2.14.5,<3.0.0)
Requires-Dist: randomname (>=0.1.5,<0.2.0)
Requires-Dist: rich (>=12.0.1,<13.0.0)
Requires-Dist: ruamel.yaml (>=0.17.21,<0.18.0)
Requires-Dist: scikit-learn (>=1.0.2,<2.0.0)
Requires-Dist: sphinx-rtd-theme (>=1.0.0,<2.0.0)
Requires-Dist: tqdm (>=4.63.0,<5.0.0)
Requires-Dist: xhtml2pdf (>=0.2.15,<0.3.0)
Requires-Dist: yacs (>=0.1.8,<0.2.0)
Project-URL: Documentation, https://uval.readthedocs.io/
Project-URL: Repository, https://gitlab.com/smithsdetection/uval
